fflinter/__init__.py
fflinter/render_jsonnet.py
fflinter/template_filters.py
fflinter/utils.py
fflinter/commands/__init__.py
fflinter/commands/cli.py
fflinter/commands/command_base.py
fflinter/commands/jsonnet.py
fflinter/commands/version.py
fflinter-0.1.0.data/scripts/fflinter
fflinter-0.1.0.dist-info/DESCRIPTION.rst
fflinter-0.1.0.dist-info/METADATA
fflinter-0.1.0.dist-info/RECORD
fflinter-0.1.0.dist-info/WHEEL
fflinter-0.1.0.dist-info/metadata.json
fflinter-0.1.0.dist-info/top_level.txt
