Metadata-Version: 2.0
Name: fflinter
Version: 0.1.0
Summary: fflinter cli
Home-page: https://github.com/ant31/fflinter
Author: Antoine Legrand
Author-email: 2t.antoine@gmail.com
License: Apache License version 2
Keywords: fflinter,fflinterpy,kubernetes
Platform: UNKNOWN
Classifier: Development Status :: 2 - Pre-Alpha
Classifier: Intended Audience :: Developers
Classifier: Natural Language :: English
Classifier: Programming Language :: Python :: 2
Classifier: Programming Language :: Python :: 2.7
Requires-Dist: futures
Requires-Dist: pyyaml
Requires-Dist: jinja2 (>=2.8)
Requires-Dist: jsonnet (>=0.9.0)
